django_utils/__init__.py
django_utils/models.py
django_utils/templatetags/__init__.py
django_utils/templatetags/django_utils.py
django_ryuutils-0.0.1.dist-info/LICENSE
django_ryuutils-0.0.1.dist-info/METADATA
django_ryuutils-0.0.1.dist-info/WHEEL
django_ryuutils-0.0.1.dist-info/top_level.txt
django_ryuutils-0.0.1.dist-info/RECORD
