Metadata-Version: 2.1
Name: django-ryuutils
Version: 0.0.1
Summary: A package of utilities for Django (template tags, etc.)
Home-page: http://github.com/ryuuzu/django-utils/
Author: Utsav Gurmachhan Magar
Author-email: "Utsav Gurmachhan Magar (ryuuzu)" <me@ryuuzu.xyz>
Project-URL: Homepage, https://github.com/ryuuzu/django-utils/
Project-URL: Bug Tracker, https://github.com/ryuuzu/django-utils/issues
Classifier: Programming Language :: Python :: 3
Classifier: License :: OSI Approved :: MIT License
Classifier: Operating System :: OS Independent
Requires-Python: >=3.7
License-File: LICENSE
